PyGeany.py
setup.py
PyGeany.egg-info/PKG-INFO
PyGeany.egg-info/SOURCES.txt
PyGeany.egg-info/dependency_links.txt
PyGeany.egg-info/requires.txt
PyGeany.egg-info/top_level.txt
PyGeany.egg-info/zip-safe