Metadata-Version: 1.0
Name: PyGeany
Version: 0.1
Summary: Provides support for geany's control socket
Home-page: https://github.com/EisenSheng/PyGeany
Author: Arthur S.
Author-email: arthur.s@redsmile.org
License: UNKNOWN
Platform: UNKNOWN
Classifier: Development Status :: 3 - Alpha
Classifier: License :: Public Domain
Classifier: Topic :: Software Development :: Libraries
